dnserver/__init__.py
dnserver/__main__.py
dnserver/cli.py
dnserver/load_records.py
dnserver/main.py
dnserver/version.py
dnserver-0.4.0.dist-info/METADATA
dnserver-0.4.0.dist-info/WHEEL
dnserver-0.4.0.dist-info/entry_points.txt
dnserver-0.4.0.dist-info/licenses/LICENSE
dnserver-0.4.0.dist-info/RECORD
