Metadata-Version: 2.1
Name: dnserver
Version: 0.4.0
Summary: Simple DNS server written in python for use in development and testing.
Project-URL: Homepage, https://github.com/samuelcolvin/dnserver
Project-URL: Documentation, https://github.com/samuelcolvin/dnserver
Project-URL: Source, https://github.com/samuelcolvin/dnserver
Project-URL: Changelog, https://github.com/samuelcolvin/dnserver/releases
Author-email: Samuel Colvin <s@muelcolvin.com>
License-File: LICENSE
Classifier: Development Status :: 4 - Beta
Classifier: Environment :: Console
Classifier: Intended Audience :: Developers
Classifier: Intended Audience :: Information Technology
Classifier: Intended Audience :: System Administrators
Classifier: License :: OSI Approved :: MIT License
Classifier: Operating System :: POSIX :: Linux
Classifier: Operating System :: Unix
Classifier: Programming Language :: Python
Classifier: Programming Language :: Python :: 3
Classifier: Programming Language :: Python :: 3 :: Only
Classifier: Programming Language :: Python :: 3.7
Classifier: Programming Language :: Python :: 3.8
Classifier: Programming Language :: Python :: 3.9
Classifier: Programming Language :: Python :: 3.10
Classifier: Programming Language :: Python :: 3.11
Classifier: Topic :: Internet
Classifier: Topic :: Internet :: Name Service (DNS)
Classifier: Topic :: Software Development :: Libraries :: Python Modules
Classifier: Topic :: Software Development :: Testing
Classifier: Topic :: Software Development :: Testing :: Mocking
Classifier: Topic :: System :: Systems Administration
Requires-Python: >=3.7
Requires-Dist: dnslib>=0.9.20
Requires-Dist: tomli; python_version < '3.11'
Requires-Dist: typing-extensions; python_version < '3.8'
